pqcdualusb/__init__ - Copy.py
pqcdualusb/__init__.py
pqcdualusb/__main__ - Copy.py
pqcdualusb/__main__.py
pqcdualusb/audit - Copy.py
pqcdualusb/audit.py
pqcdualusb/backup - Copy.py
pqcdualusb/backup.py
pqcdualusb/cli - Copy.py
pqcdualusb/cli.py
pqcdualusb/crypto - Copy.py
pqcdualusb/crypto.py
pqcdualusb/device - Copy.py
pqcdualusb/device.py
pqcdualusb/exceptions - Copy.py
pqcdualusb/exceptions.py
pqcdualusb/pqc - Copy.py
pqcdualusb/pqc.py
pqcdualusb/rust_pqc.cp311-win_amd64.pyd
pqcdualusb/rust_pqc.pyd
pqcdualusb/security - Copy.py
pqcdualusb/security.py
pqcdualusb/storage - Copy.py
pqcdualusb/storage.py
pqcdualusb/usb - Copy.py
pqcdualusb/usb.py
pqcdualusb/utils - Copy.py
pqcdualusb/utils.py
pqcdualusb/tests/__init__ - Copy.py
pqcdualusb/tests/__init__.py
pqcdualusb/tests/test_basic - Copy.py
pqcdualusb/tests/test_basic.py
pqcdualusb-0.15.2.dist-info/licenses/LICENSE
pqcdualusb-0.15.2.dist-info/METADATA
pqcdualusb-0.15.2.dist-info/WHEEL
pqcdualusb-0.15.2.dist-info/top_level.txt
pqcdualusb-0.15.2.dist-info/RECORD
