Metadata-Version: 2.4
Name: pqcdualusb
Version: 0.15.2
Summary: Post-quantum cryptography dual USB backup system with PQCRYPTO backend support
Author: Your Name
Author-email: Johnson Ajibi <ajibijohnson@jtnetsolutions.com>
License: MIT
Project-URL: Homepage, https://github.com/Johnsonajibi/PostQuantum-DualUSB-Token-Library
Project-URL: Documentation, https://github.com/Johnsonajibi/PostQuantum-DualUSB-Token-Library#readme
Project-URL: Repository, https://github.com/Johnsonajibi/PostQuantum-DualUSB-Token-Library
Project-URL: Bug Tracker, https://github.com/Johnsonajibi/PostQuantum-DualUSB-Token-Library/issues
Project-URL: Changelog, https://github.com/Johnsonajibi/PostQuantum-DualUSB-Token-Library/blob/main/CHANGELOG.md
Keywords: post-quantum,cryptography,kyber,dilithium,pqcrypto,usb,backup,encryption,security,NIST
Classifier: Development Status :: 4 - Beta
Classifier: Intended Audience :: Developers
Classifier: License :: OSI Approved :: MIT License
Classifier: Programming Language :: Python :: 3
Classifier: Programming Language :: Python :: 3.8
Classifier: Programming Language :: Python :: 3.9
Classifier: Programming Language :: Python :: 3.10
Classifier: Programming Language :: Python :: 3.11
Classifier: Programming Language :: Python :: 3.12
Classifier: Topic :: Security :: Cryptography
Classifier: Topic :: System :: Archiving :: Backup
Requires-Python: >=3.6
License-File: LICENSE
Requires-Dist: cryptography>=38.0.0
Requires-Dist: argon2-cffi>=21.0.0
Requires-Dist: pqcrypto>=0.3.4
Requires-Dist: psutil>=5.9.0
Provides-Extra: dev
Requires-Dist: pytest>=7.0.0; extra == "dev"
Requires-Dist: pytest-cov>=4.0.0; extra == "dev"
Requires-Dist: black>=23.0.0; extra == "dev"
Requires-Dist: flake8>=6.0.0; extra == "dev"
Requires-Dist: mypy>=1.0.0; extra == "dev"
Provides-Extra: cpp
Requires-Dist: cpp-pqc>=0.1.0; extra == "cpp"
Provides-Extra: rust
Requires-Dist: rust-pqc>=0.1.5; extra == "rust"
Provides-Extra: oqs
Requires-Dist: oqs>=0.8.0; extra == "oqs"
Provides-Extra: all
Requires-Dist: pqcdualusb[cpp,dev,oqs,rust]; extra == "all"
Dynamic: author
Dynamic: license-file
Dynamic: requires-python
